huaweicloudsdkcph/__init__.py
huaweicloudsdkcph/v1/__init__.py
huaweicloudsdkcph/v1/cph_async_client.py
huaweicloudsdkcph/v1/cph_client.py
huaweicloudsdkcph/v1/model/__init__.py
huaweicloudsdkcph/v1/model/add_image_member_request.py
huaweicloudsdkcph/v1/model/add_image_member_request_body.py
huaweicloudsdkcph/v1/model/add_image_member_response.py
huaweicloudsdkcph/v1/model/address.py
huaweicloudsdkcph/v1/model/bandwidth.py
huaweicloudsdkcph/v1/model/batch_create_tags_request.py
huaweicloudsdkcph/v1/model/batch_create_tags_request_body.py
huaweicloudsdkcph/v1/model/batch_create_tags_response.py
huaweicloudsdkcph/v1/model/batch_delete_tags_request.py
huaweicloudsdkcph/v1/model/batch_delete_tags_request_body.py
huaweicloudsdkcph/v1/model/batch_delete_tags_response.py
huaweicloudsdkcph/v1/model/batch_export_cloud_phone_data_request.py
huaweicloudsdkcph/v1/model/batch_export_cloud_phone_data_request_body.py
huaweicloudsdkcph/v1/model/batch_export_cloud_phone_data_response.py
huaweicloudsdkcph/v1/model/batch_import_cloud_phone_data_request.py
huaweicloudsdkcph/v1/model/batch_import_cloud_phone_data_request_body.py
huaweicloudsdkcph/v1/model/batch_import_cloud_phone_data_response.py
huaweicloudsdkcph/v1/model/batch_show_phone_connect_infos_request.py
huaweicloudsdkcph/v1/model/batch_show_phone_connect_infos_response.py
huaweicloudsdkcph/v1/model/change_cloud_phone_server_model_request.py
huaweicloudsdkcph/v1/model/change_cloud_phone_server_model_request_body.py
huaweicloudsdkcph/v1/model/change_cloud_phone_server_model_request_body_extend_param.py
huaweicloudsdkcph/v1/model/change_cloud_phone_server_model_response.py
huaweicloudsdkcph/v1/model/change_cloud_phone_server_request.py
huaweicloudsdkcph/v1/model/change_cloud_phone_server_request_body.py
huaweicloudsdkcph/v1/model/change_cloud_phone_server_request_body_band_width.py
huaweicloudsdkcph/v1/model/change_cloud_phone_server_request_body_extend_param.py
huaweicloudsdkcph-3.1.184.dist-info/METADATA
huaweicloudsdkcph-3.1.184.dist-info/WHEEL
huaweicloudsdkcph-3.1.184.dist-info/licenses/LICENSE
huaweicloudsdkcph-3.1.184.dist-info/RECORD
